NodeJsShejimoshiZhongwenDierBan/README.md
NodeJsShejimoshiZhongwenDierBan/__init__.py
NodeJsShejimoshiZhongwenDierBan/__main__.py
NodeJsShejimoshiZhongwenDierBan/file.epub
NodeJsShejimoshiZhongwenDierBan/index.html
NodeJsShejimoshiZhongwenDierBan/css/__init__.py
NodeJsShejimoshiZhongwenDierBan/css/annotations.css
NodeJsShejimoshiZhongwenDierBan/css/main.css
NodeJsShejimoshiZhongwenDierBan/css/normalize.css
NodeJsShejimoshiZhongwenDierBan/css/popup.css
NodeJsShejimoshiZhongwenDierBan/font/__init__.py
NodeJsShejimoshiZhongwenDierBan/font/fontello.eot
NodeJsShejimoshiZhongwenDierBan/font/fontello.svg
NodeJsShejimoshiZhongwenDierBan/font/fontello.ttf
NodeJsShejimoshiZhongwenDierBan/font/fontello.woff
NodeJsShejimoshiZhongwenDierBan/img/__init__.py
NodeJsShejimoshiZhongwenDierBan/img/annotator-glyph-sprite.png
NodeJsShejimoshiZhongwenDierBan/img/annotator-icon-sprite.png
NodeJsShejimoshiZhongwenDierBan/img/apple-touch-icon.png
NodeJsShejimoshiZhongwenDierBan/img/cancelfullscreen.png
NodeJsShejimoshiZhongwenDierBan/img/close.png
NodeJsShejimoshiZhongwenDierBan/img/fullscreen.png
NodeJsShejimoshiZhongwenDierBan/img/loader.gif
NodeJsShejimoshiZhongwenDierBan/img/menu-icon.png
NodeJsShejimoshiZhongwenDierBan/img/save.png
NodeJsShejimoshiZhongwenDierBan/img/saved.png
NodeJsShejimoshiZhongwenDierBan/img/settings-s.png
NodeJsShejimoshiZhongwenDierBan/img/settings.png
NodeJsShejimoshiZhongwenDierBan/img/star.png
NodeJsShejimoshiZhongwenDierBan/js/__init__.py
NodeJsShejimoshiZhongwenDierBan/js/epub.js
NodeJsShejimoshiZhongwenDierBan/js/epub.min.js
NodeJsShejimoshiZhongwenDierBan/js/epub.min.map
NodeJsShejimoshiZhongwenDierBan/js/hooks.min.js
NodeJsShejimoshiZhongwenDierBan/js/hooks.min.map
NodeJsShejimoshiZhongwenDierBan/js/reader.js
NodeJsShejimoshiZhongwenDierBan/js/reader.js.map
NodeJsShejimoshiZhongwenDierBan/js/reader.min.js
NodeJsShejimoshiZhongwenDierBan/js/reader.min.map
NodeJsShejimoshiZhongwenDierBan/js/hooks/__init__.py
node_js_shejimoshi_zhongwen_dier_ban-2024.3.3.0.dist-info/METADATA
node_js_shejimoshi_zhongwen_dier_ban-2024.3.3.0.dist-info/WHEEL
node_js_shejimoshi_zhongwen_dier_ban-2024.3.3.0.dist-info/entry_points.txt
node_js_shejimoshi_zhongwen_dier_ban-2024.3.3.0.dist-info/top_level.txt
node_js_shejimoshi_zhongwen_dier_ban-2024.3.3.0.dist-info/RECORD
